{
  "db_name": "PostgreSQL",
  "query": "\n            SELECT id, reading_datetime, cumulative_inches as \"cumulative_inches!\",\n                   incremental_inches as \"incremental_inches!\", station_id, created_at\n            FROM rain_readings\n            WHERE reading_datetime >= $1 AND reading_datetime < $2\n            ORDER BY reading_datetime DESC\n            ",
  "describe": {
    "columns": [
      {
        "ordinal": 0,
        "name": "id",
        "type_info": "Int8"
      },
      {
        "ordinal": 1,
        "name": "reading_datetime",
        "type_info": "Timestamptz"
      },
      {
        "ordinal": 2,
        "name": "cumulative_inches!",
        "type_info": "Float8"
      },
      {
        "ordinal": 3,
        "name": "incremental_inches!",
        "type_info": "Float8"
      },
      {
        "ordinal": 4,
        "name": "station_id",
        "type_info": "Varchar"
      },
      {
        "ordinal": 5,
        "name": "created_at",
        "type_info": "Timestamptz"
      }
    ],
    "parameters": {
      "Left": [
        "Timestamptz",
        "Timestamptz"
      ]
    },
    "nullable": [
      false,
      false,
      false,
      false,
      false,
      false
    ]
  },
  "hash": "78ae58eb1a09cdeab6423445143e81870de97abeb5a1601f6329ff66373eaa69"
}
